[
    {
        "date": "2021-01-26",
        "signal": "DOWN",
        "turn_up": false,
        "turn_down": true,
        "close": 113.94999694824219,
        "smooth": 114.49224945252531,
        "slope": -0.7840859984012098
    },
    {
        "date": "2021-03-04",
        "signal": "UP",
        "turn_up": true,
        "turn_down": false,
        "close": 115.5199966430664,
        "smooth": 114.0043625972202,
        "slope": 1.2605983898864679
    },
    {
        "date": "2021-09-27",
        "signal": "DOWN",
        "turn_up": false,
        "turn_down": true,
        "close": 152.0500030517578,
        "smooth": 153.08381434103987,
        "slope": -0.8552970349085598
    },
    {
        "date": "2021-10-07",
        "signal": "UP",
        "turn_up": true,
        "turn_down": false,
        "close": 153.99000549316406,
        "smooth": 151.6836081165278,
        "slope": 1.187687303653476
    },
    {
        "date": "2021-10-26",
        "signal": "DOWN",
        "turn_up": false,
        "turn_down": true,
        "close": 159.27999877929688,
        "smooth": 160.592087286946,
        "slope": -1.3410772461390223
    },
    {
        "date": "2021-12-28",
        "signal": "UP",
        "turn_up": true,
        "turn_down": false,
        "close": 165.13999938964844,
        "smooth": 163.30608279506694,
        "slope": 1.062526838361606
    },
    {
        "date": "2022-01-07",
        "signal": "DOWN",
        "turn_up": false,
        "turn_down": true,
        "close": 161.75999450683594,
        "smooth": 162.74089314407823,
        "slope": -0.8704552296084813
    },
    {
        "date": "2022-03-01",
        "signal": "UP",
        "turn_up": true,
        "turn_down": false,
        "close": 146.5800018310547,
        "smooth": 144.59950836620808,
        "slope": 1.5488574989941952
    },
    {
        "date": "2022-03-08",
        "signal": "DOWN",
        "turn_up": false,
        "turn_down": true,
        "close": 147.9600067138672,
        "smooth": 151.45588385735908,
        "slope": -1.2401739858088376
    },
    {
        "date": "2022-03-14",
        "signal": "UP",
        "turn_up": true,
        "turn_down": false,
        "close": 154.4499969482422,
        "smooth": 152.391181350158,
        "slope": 1.0724407756991212
    },
    {
        "date": "2022-04-12",
        "signal": "DOWN",
        "turn_up": false,
        "turn_down": true,
        "close": 161.85000610351562,
        "smooth": 162.75183166571327,
        "slope": -0.7912302353910547
    },
    {
        "date": "2022-04-26",
        "signal": "UP",
        "turn_up": true,
        "turn_down": false,
        "close": 164.14999389648438,
        "smooth": 160.2851968611656,
        "slope": 2.362198032324315
    },
    {
        "date": "2022-04-29",
        "signal": "DOWN",
        "turn_up": false,
        "turn_down": true,
        "close": 164.44000244140625,
        "smooth": 164.98385121311634,
        "slope": -1.2165198939081137
    },
    {
        "date": "2022-05-26",
        "signal": "UP",
        "turn_up": true,
        "turn_down": false,
        "close": 157.99000549316406,
        "smooth": 156.7334279768504,
        "slope": 1.1150128166157316
    },
    {
        "date": "2022-06-08",
        "signal": "DOWN",
        "turn_up": false,
        "turn_down": true,
        "close": 157.05999755859375,
        "smooth": 158.3032923403699,
        "slope": -1.2343155056361184
    },
    {
        "date": "2022-06-23",
        "signal": "UP",
        "turn_up": true,
        "turn_down": false,
        "close": 147.19000244140625,
        "smooth": 145.39769017422978,
        "slope": 1.3802215970942626
    },
    {
        "date": "2022-08-30",
        "signal": "DOWN",
        "turn_up": false,
        "turn_down": true,
        "close": 170.72999572753906,
        "smooth": 171.95622612833708,
        "slope": -0.8664477505248698
    },
    {
        "date": "2022-09-07",
        "signal": "UP",
        "turn_up": true,
        "turn_down": false,
        "close": 173.72999572753906,
        "smooth": 171.07225500699624,
        "slope": 1.191061578548556
    },
    {
        "date": "2022-09-21",
        "signal": "DOWN",
        "turn_up": false,
        "turn_down": true,
        "close": 168.88999938964844,
        "smooth": 169.8964562848183,
        "slope": -0.8230574010938909
    },
    {
        "date": "2022-10-03",
        "signal": "UP",
        "turn_up": true,
        "turn_down": false,
        "close": 165.08999633789062,
        "smooth": 163.53365033084435,
        "slope": 1.2667146273646637
    },
    {
        "date": "2022-10-06",
        "signal": "DOWN",
        "turn_up": false,
        "turn_down": true,
        "close": 159.39999389648438,
        "smooth": 163.4501492261646,
        "slope": -2.6011880047105223
    },
    {
        "date": "2022-10-17",
        "signal": "UP",
        "turn_up": true,
        "turn_down": false,
        "close": 157.82000732421875,
        "smooth": 156.71927444548288,
        "slope": 1.0955419767104075
    },
    {
        "date": "2022-10-26",
        "signal": "DOWN",
        "turn_up": false,
        "turn_down": true,
        "close": 159.97000122070312,
        "smooth": 161.42679617420373,
        "slope": -0.9667320571788309
    },
    {
        "date": "2022-11-18",
        "signal": "UP",
        "turn_up": true,
        "turn_down": false,
        "close": 161.17999267578125,
        "smooth": 159.37699546450813,
        "slope": 1.1164276097728418
    },
    {
        "date": "2022-12-15",
        "signal": "DOWN",
        "turn_up": false,
        "turn_down": true,
        "close": 163.3699951171875,
        "smooth": 165.43852801247252,
        "slope": -1.2309446649110924
    },
    {
        "date": "2023-03-14",
        "signal": "UP",
        "turn_up": true,
        "turn_down": false,
        "close": 154.36000061035156,
        "smooth": 151.80091804925343,
        "slope": 1.2981085572531583
    },
    {
        "date": "2023-03-22",
        "signal": "DOWN",
        "turn_up": false,
        "turn_down": true,
        "close": 152.08999633789062,
        "smooth": 153.46641485803963,
        "slope": -0.8797431071200918
    },
    {
        "date": "2023-03-29",
        "signal": "UP",
        "turn_up": true,
        "turn_down": false,
        "close": 157.0399932861328,
        "smooth": 155.00062042004072,
        "slope": 1.7388472804120028
    },
    {
        "date": "2023-04-26",
        "signal": "DOWN",
        "turn_up": false,
        "turn_down": true,
        "close": 163.61000061035156,
        "smooth": 164.8090771184327,
        "slope": -0.9041601147124112
    },
    {
        "date": "2023-06-29",
        "signal": "UP",
        "turn_up": true,
        "turn_down": false,
        "close": 169.61000061035156,
        "smooth": 168.02726842455974,
        "slope": 1.4077792371863467
    },
    {
        "date": "2023-07-26",
        "signal": "DOWN",
        "turn_up": false,
        "turn_down": true,
        "close": 164.94000244140625,
        "smooth": 168.92443227028937,
        "slope": -1.999650269078117
    },
    {
        "date": "2023-10-13",
        "signal": "UP",
        "turn_up": true,
        "turn_down": false,
        "close": 158.80999755859375,
        "smooth": 156.8863172320819,
        "slope": 1.0660435005409568
    },
    {
        "date": "2024-04-03",
        "signal": "DOWN",
        "turn_up": false,
        "turn_down": true,
        "close": 210.4199981689453,
        "smooth": 211.56739485480892,
        "slope": -1.1223023977158846
    },
    {
        "date": "2024-04-24",
        "signal": "UP",
        "turn_up": true,
        "turn_down": false,
        "close": 210.42999267578125,
        "smooth": 208.4808008007889,
        "slope": 1.2998550378127618
    },
    {
        "date": "2024-04-30",
        "signal": "DOWN",
        "turn_up": false,
        "turn_down": true,
        "close": 208.02000427246094,
        "smooth": 209.7976905642696,
        "slope": -1.040342217496601
    },
    {
        "date": "2024-06-14",
        "signal": "UP",
        "turn_up": true,
        "turn_down": false,
        "close": 203.63999938964844,
        "smooth": 202.3068241950948,
        "slope": 1.1017514785607148
    },
    {
        "date": "2024-07-01",
        "signal": "DOWN",
        "turn_up": false,
        "turn_down": true,
        "close": 209.36000061035156,
        "smooth": 211.22381828306703,
        "slope": -0.8344042810277017
    },
    {
        "date": "2024-07-12",
        "signal": "UP",
        "turn_up": true,
        "turn_down": false,
        "close": 213.75,
        "smooth": 212.0086381830376,
        "slope": 1.2010319995361414
    },
    {
        "date": "2024-07-23",
        "signal": "DOWN",
        "turn_up": false,
        "turn_down": true,
        "close": 218.72999572753906,
        "smooth": 220.82296221993312,
        "slope": -1.2009399572767023
    },
    {
        "date": "2024-08-01",
        "signal": "UP",
        "turn_up": true,
        "turn_down": false,
        "close": 206.07000732421875,
        "smooth": 204.18009352528733,
        "slope": 1.1687926543160359
    },
    {
        "date": "2024-08-05",
        "signal": "DOWN",
        "turn_up": false,
        "turn_down": true,
        "close": 201.5399932861328,
        "smooth": 204.05730938369476,
        "slope": -0.8669720076090357
    },
    {
        "date": "2024-10-08",
        "signal": "UP",
        "turn_up": true,
        "turn_down": false,
        "close": 208.67999267578125,
        "smooth": 207.6194556960408,
        "slope": 1.1219068312083778
    },
    {
        "date": "2024-10-24",
        "signal": "DOWN",
        "turn_up": false,
        "turn_down": true,
        "close": 208.91000366210938,
        "smooth": 210.82498639557718,
        "slope": -1.2555171782143333
    },
    {
        "date": "2024-10-29",
        "signal": "UP",
        "turn_up": true,
        "turn_down": false,
        "close": 219.11000061035156,
        "smooth": 212.60958475859601,
        "slope": 2.2104034850149077
    },
    {
        "date": "2024-11-14",
        "signal": "DOWN",
        "turn_up": false,
        "turn_down": true,
        "close": 221.72000122070312,
        "smooth": 222.96650480468196,
        "slope": -1.2554929724766453
    },
    {
        "date": "2024-11-21",
        "signal": "UP",
        "turn_up": true,
        "turn_down": false,
        "close": 221.52999877929688,
        "smooth": 220.16274614517988,
        "slope": 1.1424456437228088
    },
    {
        "date": "2024-12-05",
        "signal": "DOWN",
        "turn_up": false,
        "turn_down": true,
        "close": 224.0500030517578,
        "smooth": 225.0461095291816,
        "slope": -0.7896529822654657
    },
    {
        "date": "2025-01-08",
        "signal": "UP",
        "turn_up": true,
        "turn_down": false,
        "close": 206.5800018310547,
        "smooth": 203.93627713139634,
        "slope": 1.3315228130673091
    },
    {
        "date": "2025-03-05",
        "signal": "DOWN",
        "turn_up": false,
        "turn_down": true,
        "close": 230.38999938964844,
        "smooth": 230.83887256475975,
        "slope": -0.9992387346925966
    },
    {
        "date": "2025-03-31",
        "signal": "UP",
        "turn_up": true,
        "turn_down": false,
        "close": 231.50999450683594,
        "smooth": 229.2131300142839,
        "slope": 1.4609689503795096
    },
    {
        "date": "2025-04-04",
        "signal": "DOWN",
        "turn_up": false,
        "turn_down": true,
        "close": 225.1999969482422,
        "smooth": 230.7488292409506,
        "slope": -3.3739518518933806
    },
    {
        "date": "2025-04-10",
        "signal": "UP",
        "turn_up": true,
        "turn_down": false,
        "close": 226.4499969482422,
        "smooth": 224.68222987116602,
        "slope": 1.3349414047962114
    },
    {
        "date": "2025-05-09",
        "signal": "DOWN",
        "turn_up": false,
        "turn_down": true,
        "close": 232.75,
        "smooth": 233.45023586698025,
        "slope": -1.607031748986742
    },
    {
        "date": "2025-05-16",
        "signal": "UP",
        "turn_up": true,
        "turn_down": false,
        "close": 229.8699951171875,
        "smooth": 227.77207592619212,
        "slope": 1.3339755497336796
    },
    {
        "date": "2025-06-06",
        "signal": "DOWN",
        "turn_up": false,
        "turn_down": true,
        "close": 236.3300018310547,
        "smooth": 238.16026684748005,
        "slope": -1.2578934982804952
    },
    {
        "date": "2025-07-29",
        "signal": "UP",
        "turn_up": true,
        "turn_down": false,
        "close": 235.55999755859375,
        "smooth": 231.01879595737103,
        "slope": 1.5346966682273546
    },
    {
        "date": "2025-07-31",
        "signal": "DOWN",
        "turn_up": false,
        "turn_down": true,
        "close": 229.16000366210938,
        "smooth": 230.69570963914046,
        "slope": -0.7539047295604178
    },
    {
        "date": "2025-08-07",
        "signal": "UP",
        "turn_up": true,
        "turn_down": false,
        "close": 233.22000122070312,
        "smooth": 231.54778464230083,
        "slope": 1.1012758577149526
    },
    {
        "date": "2025-08-12",
        "signal": "DOWN",
        "turn_up": false,
        "turn_down": true,
        "close": 232.97999572753906,
        "smooth": 233.86001771602506,
        "slope": -0.9549937225640548
    },
    {
        "date": "2025-11-13",
        "signal": "UP",
        "turn_up": true,
        "turn_down": false,
        "close": 204.50999450683594,
        "smooth": 203.15732111487708,
        "slope": 1.4546136138343257
    },
    {
        "date": "2025-12-05",
        "signal": "DOWN",
        "turn_up": false,
        "turn_down": true,
        "close": 213.5800018310547,
        "smooth": 214.6319127048614,
        "slope": -1.082128642577075
    },
    {
        "date": "2025-12-11",
        "signal": "UP",
        "turn_up": true,
        "turn_down": false,
        "close": 212.0500030517578,
        "smooth": 211.24458078393045,
        "slope": 1.0067888872481916
    },
    {
        "date": "2026-01-02",
        "signal": "DOWN",
        "turn_up": false,
        "turn_down": true,
        "close": 218.39999389648438,
        "smooth": 219.9343929340211,
        "slope": -0.8565898773316007
    },
    {
        "date": "2026-01-09",
        "signal": "UP",
        "turn_up": true,
        "turn_down": false,
        "close": 220.91000366210938,
        "smooth": 219.11113734651758,
        "slope": 1.004230737189772
    },
    {
        "date": "2026-01-13",
        "signal": "DOWN",
        "turn_up": false,
        "turn_down": true,
        "close": 216.17999267578125,
        "smooth": 217.93662187351558,
        "slope": -0.9806515464321421
    },
    {
        "date": "2026-01-20",
        "signal": "UP",
        "turn_up": true,
        "turn_down": false,
        "close": 221.3000030517578,
        "smooth": 220.2633359584334,
        "slope": 1.4047393727300772
    },
    {
        "date": "2026-01-29",
        "signal": "DOWN",
        "turn_up": false,
        "turn_down": true,
        "close": 223.1300048828125,
        "smooth": 227.5179380108348,
        "slope": -2.4495968831588755
    },
    {
        "date": "2026-02-09",
        "signal": "UP",
        "turn_up": true,
        "turn_down": false,
        "close": 230.5,
        "smooth": 227.73093951734398,
        "slope": 1.5458489748338025
    }
]