[
    {
        "date": "2020-12-15",
        "signal": "UP",
        "turn_up": true,
        "turn_down": false,
        "close": 59.835269927978516,
        "smooth": 59.062659346489006,
        "slope": 0.2845977135222917
    },
    {
        "date": "2020-12-17",
        "signal": "DOWN",
        "turn_up": false,
        "turn_down": true,
        "close": 59.137596130371094,
        "smooth": 59.178021891089436,
        "slope": -0.2806208465613089
    },
    {
        "date": "2020-12-24",
        "signal": "UP",
        "turn_up": true,
        "turn_down": false,
        "close": 59.195735931396484,
        "smooth": 58.8170350283136,
        "slope": 0.291573426212242
    },
    {
        "date": "2021-01-04",
        "signal": "DOWN",
        "turn_up": false,
        "turn_down": true,
        "close": 58.003875732421875,
        "smooth": 59.0243181595232,
        "slope": -0.415552906050042
    },
    {
        "date": "2021-01-21",
        "signal": "UP",
        "turn_up": true,
        "turn_down": false,
        "close": 57.25775146484375,
        "smooth": 56.92648840515012,
        "slope": 0.2819848617272811
    },
    {
        "date": "2021-02-18",
        "signal": "DOWN",
        "turn_up": false,
        "turn_down": true,
        "close": 59.031009674072266,
        "smooth": 59.66358456504951,
        "slope": -0.2603750177726276
    },
    {
        "date": "2021-03-10",
        "signal": "UP",
        "turn_up": true,
        "turn_down": false,
        "close": 59.5155029296875,
        "smooth": 58.90051086581794,
        "slope": 0.35125507557633995
    },
    {
        "date": "2021-03-18",
        "signal": "DOWN",
        "turn_up": false,
        "turn_down": true,
        "close": 61.25,
        "smooth": 61.338511267356374,
        "slope": -0.2939798367990676
    },
    {
        "date": "2021-03-24",
        "signal": "UP",
        "turn_up": true,
        "turn_down": false,
        "close": 61.269378662109375,
        "smooth": 60.9728534282296,
        "slope": 0.2539158401002659
    },
    {
        "date": "2021-05-05",
        "signal": "DOWN",
        "turn_up": false,
        "turn_down": true,
        "close": 65.05814361572266,
        "smooth": 66.20605681977726,
        "slope": -0.4548746529787806
    },
    {
        "date": "2021-05-19",
        "signal": "UP",
        "turn_up": true,
        "turn_down": false,
        "close": 63.62403106689453,
        "smooth": 63.5358768031816,
        "slope": 0.2573657871771218
    },
    {
        "date": "2021-06-15",
        "signal": "DOWN",
        "turn_up": false,
        "turn_down": true,
        "close": 67.45155334472656,
        "smooth": 68.06034649633546,
        "slope": -0.4803303890134316
    },
    {
        "date": "2021-07-09",
        "signal": "UP",
        "turn_up": true,
        "turn_down": false,
        "close": 66.7344970703125,
        "smooth": 66.1167231074867,
        "slope": 0.3577361327990616
    },
    {
        "date": "2021-09-08",
        "signal": "DOWN",
        "turn_up": false,
        "turn_down": true,
        "close": 69.47674560546875,
        "smooth": 69.5943970951018,
        "slope": -0.40627108565308134
    },
    {
        "date": "2021-10-05",
        "signal": "UP",
        "turn_up": true,
        "turn_down": false,
        "close": 64.19573974609375,
        "smooth": 64.03952726232862,
        "slope": 0.3319463007477381
    },
    {
        "date": "2021-10-29",
        "signal": "DOWN",
        "turn_up": false,
        "turn_down": true,
        "close": 69.21511840820312,
        "smooth": 70.21344646381789,
        "slope": -0.5564295930662979
    },
    {
        "date": "2021-11-11",
        "signal": "UP",
        "turn_up": true,
        "turn_down": false,
        "close": 70.1744155883789,
        "smooth": 69.48707612657665,
        "slope": 0.37052303021545896
    },
    {
        "date": "2021-11-26",
        "signal": "DOWN",
        "turn_up": false,
        "turn_down": true,
        "close": 69.47000122070312,
        "smooth": 70.18450963568309,
        "slope": -0.2683160626714809
    },
    {
        "date": "2021-12-07",
        "signal": "UP",
        "turn_up": true,
        "turn_down": false,
        "close": 68.38999938964844,
        "smooth": 68.01546668176493,
        "slope": 0.254031525397977
    },
    {
        "date": "2021-12-09",
        "signal": "DOWN",
        "turn_up": false,
        "turn_down": true,
        "close": 67.36000061035156,
        "smooth": 67.9725074395779,
        "slope": -0.3559196524601802
    },
    {
        "date": "2021-12-21",
        "signal": "UP",
        "turn_up": true,
        "turn_down": false,
        "close": 68.7300033569336,
        "smooth": 67.93880126253784,
        "slope": 0.4360164398492472
    },
    {
        "date": "2022-01-14",
        "signal": "DOWN",
        "turn_up": false,
        "turn_down": true,
        "close": 71.5,
        "smooth": 71.57986515746296,
        "slope": -0.35365616062651384
    },
    {
        "date": "2022-01-28",
        "signal": "UP",
        "turn_up": true,
        "turn_down": false,
        "close": 69.48999786376953,
        "smooth": 68.65325300394228,
        "slope": 0.36911540162210343
    },
    {
        "date": "2022-02-03",
        "signal": "DOWN",
        "turn_up": false,
        "turn_down": true,
        "close": 68.66999816894531,
        "smooth": 69.06489268721009,
        "slope": -0.2669444535053529
    },
    {
        "date": "2022-03-16",
        "signal": "UP",
        "turn_up": true,
        "turn_down": false,
        "close": 65.5999984741211,
        "smooth": 65.28887807122202,
        "slope": 0.3019977887470233
    },
    {
        "date": "2022-04-22",
        "signal": "DOWN",
        "turn_up": false,
        "turn_down": true,
        "close": 73.54000091552734,
        "smooth": 73.85645074877819,
        "slope": -0.28652743540087755
    },
    {
        "date": "2022-05-12",
        "signal": "UP",
        "turn_up": true,
        "turn_down": false,
        "close": 65.38999938964844,
        "smooth": 65.02608947953273,
        "slope": 0.5286053814362504
    },
    {
        "date": "2022-06-03",
        "signal": "DOWN",
        "turn_up": false,
        "turn_down": true,
        "close": 67.36000061035156,
        "smooth": 68.0098275312867,
        "slope": -0.36585655159279185
    },
    {
        "date": "2022-06-21",
        "signal": "UP",
        "turn_up": true,
        "turn_down": false,
        "close": 65.47000122070312,
        "smooth": 64.91971311719767,
        "slope": 0.41697184280811683
    },
    {
        "date": "2022-07-13",
        "signal": "DOWN",
        "turn_up": false,
        "turn_down": true,
        "close": 68.05000305175781,
        "smooth": 68.84417953454478,
        "slope": -0.29228696416872424
    },
    {
        "date": "2022-07-15",
        "signal": "UP",
        "turn_up": true,
        "turn_down": false,
        "close": 70.30999755859375,
        "smooth": 69.2786937800564,
        "slope": 0.32213523976519554
    },
    {
        "date": "2022-08-02",
        "signal": "DOWN",
        "turn_up": false,
        "turn_down": true,
        "close": 72.80000305175781,
        "smooth": 73.04412308018425,
        "slope": -0.25517342534779175
    },
    {
        "date": "2022-08-09",
        "signal": "UP",
        "turn_up": true,
        "turn_down": false,
        "close": 73.55000305175781,
        "smooth": 73.11526685867167,
        "slope": 0.3031148077195738
    },
    {
        "date": "2022-08-18",
        "signal": "DOWN",
        "turn_up": false,
        "turn_down": true,
        "close": 72.98999786376953,
        "smooth": 73.5671940174028,
        "slope": -0.2788337706164299
    },
    {
        "date": "2022-10-17",
        "signal": "UP",
        "turn_up": true,
        "turn_down": false,
        "close": 57.4900016784668,
        "smooth": 57.17346683535822,
        "slope": 0.3492611931445495
    },
    {
        "date": "2022-11-28",
        "signal": "DOWN",
        "turn_up": false,
        "turn_down": true,
        "close": 61.7400016784668,
        "smooth": 63.71041367877621,
        "slope": -0.8026445320340976
    },
    {
        "date": "2022-12-07",
        "signal": "UP",
        "turn_up": true,
        "turn_down": false,
        "close": 63.56999969482422,
        "smooth": 63.02144501874096,
        "slope": 0.3391520544633977
    },
    {
        "date": "2022-12-16",
        "signal": "DOWN",
        "turn_up": false,
        "turn_down": true,
        "close": 63.47999954223633,
        "smooth": 64.16501829585371,
        "slope": -0.3031670560107784
    },
    {
        "date": "2023-01-11",
        "signal": "UP",
        "turn_up": true,
        "turn_down": false,
        "close": 66.0,
        "smooth": 64.82751041233536,
        "slope": 0.6358236069710301
    },
    {
        "date": "2023-02-08",
        "signal": "DOWN",
        "turn_up": false,
        "turn_down": true,
        "close": 67.22000122070312,
        "smooth": 67.46614659735036,
        "slope": -0.2901350962848781
    },
    {
        "date": "2023-03-28",
        "signal": "UP",
        "turn_up": true,
        "turn_down": false,
        "close": 61.060001373291016,
        "smooth": 60.79330292314689,
        "slope": 0.2977627106054719
    },
    {
        "date": "2023-04-13",
        "signal": "DOWN",
        "turn_up": false,
        "turn_down": true,
        "close": 61.529998779296875,
        "smooth": 61.99547017561964,
        "slope": -0.3494433664951906
    },
    {
        "date": "2023-04-27",
        "signal": "UP",
        "turn_up": true,
        "turn_down": false,
        "close": 62.290000915527344,
        "smooth": 61.94097948861244,
        "slope": 0.25846240574677637
    },
    {
        "date": "2023-05-02",
        "signal": "DOWN",
        "turn_up": false,
        "turn_down": true,
        "close": 61.38999938964844,
        "smooth": 61.94497829407558,
        "slope": -0.3295570454635772
    },
    {
        "date": "2023-05-04",
        "signal": "UP",
        "turn_up": true,
        "turn_down": false,
        "close": 61.91999816894531,
        "smooth": 61.711872889890806,
        "slope": 0.2798780974793509
    },
    {
        "date": "2023-05-15",
        "signal": "DOWN",
        "turn_up": false,
        "turn_down": true,
        "close": 61.939998626708984,
        "smooth": 62.044786436706545,
        "slope": -0.34358189196285593
    },
    {
        "date": "2023-06-06",
        "signal": "UP",
        "turn_up": true,
        "turn_down": false,
        "close": 60.0099983215332,
        "smooth": 59.74667654126417,
        "slope": 0.2980069965833678
    },
    {
        "date": "2023-06-20",
        "signal": "DOWN",
        "turn_up": false,
        "turn_down": true,
        "close": 60.33000183105469,
        "smooth": 60.88334785603484,
        "slope": -0.3825479481789209
    },
    {
        "date": "2023-07-19",
        "signal": "UP",
        "turn_up": true,
        "turn_down": false,
        "close": 61.72999954223633,
        "smooth": 61.18475086488455,
        "slope": 0.4092888427479089
    },
    {
        "date": "2023-07-27",
        "signal": "DOWN",
        "turn_up": false,
        "turn_down": true,
        "close": 62.189998626708984,
        "smooth": 62.77375145967783,
        "slope": -0.3964814147818565
    },
    {
        "date": "2023-11-01",
        "signal": "UP",
        "turn_up": true,
        "turn_down": false,
        "close": 47.9900016784668,
        "smooth": 47.95283617749999,
        "slope": 0.3824535737028434
    },
    {
        "date": "2024-01-16",
        "signal": "DOWN",
        "turn_up": false,
        "turn_down": true,
        "close": 58.34000015258789,
        "smooth": 58.747758624721634,
        "slope": -0.3892741244764295
    },
    {
        "date": "2024-03-26",
        "signal": "UP",
        "turn_up": true,
        "turn_down": false,
        "close": 52.599998474121094,
        "smooth": 52.35866354571026,
        "slope": 0.32017459121034264
    },
    {
        "date": "2024-04-10",
        "signal": "DOWN",
        "turn_up": false,
        "turn_down": true,
        "close": 52.13999938964844,
        "smooth": 53.08545317314703,
        "slope": -0.4153480644284393
    },
    {
        "date": "2024-04-18",
        "signal": "UP",
        "turn_up": true,
        "turn_down": false,
        "close": 52.029998779296875,
        "smooth": 51.721414640588684,
        "slope": 0.3223314726449402
    },
    {
        "date": "2024-05-22",
        "signal": "DOWN",
        "turn_up": false,
        "turn_down": true,
        "close": 53.720001220703125,
        "smooth": 54.577381281236704,
        "slope": -0.6454724618355954
    },
    {
        "date": "2024-05-31",
        "signal": "UP",
        "turn_up": true,
        "turn_down": false,
        "close": 53.060001373291016,
        "smooth": 52.36215639632895,
        "slope": 0.3645749392142861
    },
    {
        "date": "2024-06-07",
        "signal": "DOWN",
        "turn_up": false,
        "turn_down": true,
        "close": 53.31999969482422,
        "smooth": 53.6411055964045,
        "slope": -0.25641787803655447
    },
    {
        "date": "2024-07-10",
        "signal": "UP",
        "turn_up": true,
        "turn_down": false,
        "close": 53.58000183105469,
        "smooth": 53.10407556559614,
        "slope": 0.47245936001540656
    },
    {
        "date": "2024-09-18",
        "signal": "DOWN",
        "turn_up": false,
        "turn_down": true,
        "close": 62.189998626708984,
        "smooth": 62.439989759555985,
        "slope": -0.3814618355477606
    },
    {
        "date": "2024-10-14",
        "signal": "UP",
        "turn_up": true,
        "turn_down": false,
        "close": 62.11000061035156,
        "smooth": 61.87063395505113,
        "slope": 0.3336025626110022
    },
    {
        "date": "2024-10-24",
        "signal": "DOWN",
        "turn_up": false,
        "turn_down": true,
        "close": 63.310001373291016,
        "smooth": 63.718163874424135,
        "slope": -0.5453011252240891
    },
    {
        "date": "2025-01-15",
        "signal": "UP",
        "turn_up": true,
        "turn_down": false,
        "close": 53.16999816894531,
        "smooth": 52.83719107439432,
        "slope": 0.405083612743411
    },
    {
        "date": "2025-03-11",
        "signal": "DOWN",
        "turn_up": false,
        "turn_down": true,
        "close": 56.709999084472656,
        "smooth": 57.582582665991154,
        "slope": -0.46077184539555205
    },
    {
        "date": "2025-03-28",
        "signal": "UP",
        "turn_up": true,
        "turn_down": false,
        "close": 56.61000061035156,
        "smooth": 56.35712316362692,
        "slope": 0.3666628927699378
    },
    {
        "date": "2025-04-04",
        "signal": "DOWN",
        "turn_up": false,
        "turn_down": true,
        "close": 55.150001525878906,
        "smooth": 56.3743238571438,
        "slope": -0.9587210966077855
    },
    {
        "date": "2025-04-11",
        "signal": "UP",
        "turn_up": true,
        "turn_down": false,
        "close": 55.220001220703125,
        "smooth": 54.49822100756282,
        "slope": 0.5188463335044453
    },
    {
        "date": "2025-04-24",
        "signal": "DOWN",
        "turn_up": false,
        "turn_down": true,
        "close": 57.150001525878906,
        "smooth": 57.617210067109404,
        "slope": -0.2606757172466594
    },
    {
        "date": "2025-06-09",
        "signal": "UP",
        "turn_up": true,
        "turn_down": false,
        "close": 56.810001373291016,
        "smooth": 56.29606141836424,
        "slope": 0.33224589905043445
    },
    {
        "date": "2025-07-15",
        "signal": "DOWN",
        "turn_up": false,
        "turn_down": true,
        "close": 56.65999984741211,
        "smooth": 57.34224032060554,
        "slope": -0.2893549277097449
    },
    {
        "date": "2025-07-22",
        "signal": "UP",
        "turn_up": true,
        "turn_down": false,
        "close": 57.84000015258789,
        "smooth": 57.04638717808367,
        "slope": 0.3708444682036749
    },
    {
        "date": "2025-07-30",
        "signal": "DOWN",
        "turn_up": false,
        "turn_down": true,
        "close": 56.790000915527344,
        "smooth": 57.171626921251814,
        "slope": -0.29310797644026465
    },
    {
        "date": "2025-08-19",
        "signal": "UP",
        "turn_up": true,
        "turn_down": false,
        "close": 59.0099983215332,
        "smooth": 58.313786123821735,
        "slope": 0.4784697019925197
    },
    {
        "date": "2025-08-25",
        "signal": "DOWN",
        "turn_up": false,
        "turn_down": true,
        "close": 58.209999084472656,
        "smooth": 58.75298738879905,
        "slope": -0.26315844805748156
    },
    {
        "date": "2025-09-05",
        "signal": "UP",
        "turn_up": true,
        "turn_down": false,
        "close": 59.290000915527344,
        "smooth": 58.583292817581686,
        "slope": 0.2898194288792091
    },
    {
        "date": "2025-10-07",
        "signal": "DOWN",
        "turn_up": false,
        "turn_down": true,
        "close": 59.630001068115234,
        "smooth": 59.97923686600711,
        "slope": -0.27110028645831363
    },
    {
        "date": "2025-10-17",
        "signal": "UP",
        "turn_up": true,
        "turn_down": false,
        "close": 59.939998626708984,
        "smooth": 59.430715149601156,
        "slope": 0.3587732943915647
    },
    {
        "date": "2025-10-28",
        "signal": "DOWN",
        "turn_up": false,
        "turn_down": true,
        "close": 59.209999084472656,
        "smooth": 59.83636840390964,
        "slope": -0.4392976756385849
    }
]